loopedlist/__init__.py
loopedlist/loopedlist.py
loopedlist-0.0.2.dist-info/LICENSE
loopedlist-0.0.2.dist-info/METADATA
loopedlist-0.0.2.dist-info/WHEEL
loopedlist-0.0.2.dist-info/top_level.txt
loopedlist-0.0.2.dist-info/RECORD
